subsidiary_parent_score_country/__init__.py
subsidiary_parent_score_country/matching_function.py
subsidiary_parent_score_country/data/countries_name.csv
subsidiary_parent_score_country-0.0.9.dist-info/LICENSE
subsidiary_parent_score_country-0.0.9.dist-info/METADATA
subsidiary_parent_score_country-0.0.9.dist-info/WHEEL
subsidiary_parent_score_country-0.0.9.dist-info/top_level.txt
subsidiary_parent_score_country-0.0.9.dist-info/RECORD
