Metadata-Version: 2.1
Name: subsidiary-parent-score-country
Version: 0.0.9
Summary: Returns a score of 2 companies to be subsidiaries or parent
Home-page: UNKNOWN
Author: camillebrl (Camille Barboule)
Author-email: camille.barboule@gmail.com
License: UNKNOWN
Keywords: python,subsidiary,matching,parent,country,name
Platform: UNKNOWN
Classifier: Development Status :: 1 - Planning
Classifier: Intended Audience :: Developers
Classifier: Programming Language :: Python :: 3
Classifier: Operating System :: Unix
Classifier: Operating System :: MacOS :: MacOS X
Classifier: Operating System :: Microsoft :: Windows
Requires-Dist: company-name-matching (==0.2.5)
